nebpyclient/VERSION
nebpyclient/__init__.py
nebpyclient/api/__init__.py
nebpyclient/api/alerts.py
nebpyclient/api/auditing.py
nebpyclient/api/common.py
nebpyclient/api/constants.py
nebpyclient/api/datacenters.py
nebpyclient/api/etickets.py
nebpyclient/api/filters.py
nebpyclient/api/graphqlclient.py
nebpyclient/api/hosts.py
nebpyclient/api/issues.py
nebpyclient/api/keyvalue.py
nebpyclient/api/lom.py
nebpyclient/api/luns.py
nebpyclient/api/metadata.py
nebpyclient/api/npodgroups.py
nebpyclient/api/npods.py
nebpyclient/api/npodtemplates.py
nebpyclient/api/physicaldrives.py
nebpyclient/api/racks.py
nebpyclient/api/rbac.py
nebpyclient/api/recipe.py
nebpyclient/api/recipeclient.py
nebpyclient/api/rooms.py
nebpyclient/api/rows.py
nebpyclient/api/session.py
nebpyclient/api/snapshots.py
nebpyclient/api/sorting.py
nebpyclient/api/spus.py
nebpyclient/api/tokens.py
nebpyclient/api/updates.py
nebpyclient/api/usergroups.py
nebpyclient/api/users.py
nebpyclient/api/volumes.py
nebpyclient/api/vsphere.py
nebpyclient/api/webhooks.py
nebpyclient-2.0.10.dist-info/LICENSE
nebpyclient-2.0.10.dist-info/METADATA
nebpyclient-2.0.10.dist-info/WHEEL
nebpyclient-2.0.10.dist-info/top_level.txt
nebpyclient-2.0.10.dist-info/RECORD
