Metadata-Version: 2.1
Name: nebpyclient
Version: 2.0.10
Summary: The Nebulon Python SDK
Home-page: https://github.com/Nebulon/nebpyclient
Author: Nebulon, Inc.
Author-email: info@nebulon.com
License: UNKNOWN
Platform: UNKNOWN
Classifier: Programming Language :: Python :: 3
Classifier: License :: OSI Approved :: MIT License
Classifier: Operating System :: OS Independent
Requires-Python: >=3.6
License-File: LICENSE
Requires-Dist: requests
